{
  "name": "Climate control gate",
  "group": "process",
  "description": "Climate control gate",
  "inputs": [
    {
      "id": "climate_control",
      "description": "Climate control",
      "name": "Climate control",
      "abbrev": "CC",
      "type": "NUMBER",
      "default": "0"
    }
  ],
  "outputs": [
    {
      "id": "heating",
      "description": "Heating output",
      "name": "Heating",
      "abbrev": "H",
      "type": "BOOLEAN",
      "default": "false"
    },
    {
      "id": "cooling",
      "description": "Cooling output",
      "name": "Cooling",
      "abbrev": "C",
      "type": "BOOLEAN",
      "default": "false"
    }
  ],
  "config": [
  ],
  "state": [
  ]
}
